daal4py/__init__.py
daal4py/__main__.py
daal4py/_daal4py.cpython-310-x86_64-linux-gnu.so
daal4py/mpi_transceiver.cpython-310-x86_64-linux-gnu.so
daal4py/mb/__init__.py
daal4py/mb/gbt_convertors.py
daal4py/mb/logistic_regression_builders.py
daal4py/mb/tree_based_builders.py
daal4py/sklearn/__init__.py
daal4py/sklearn/_n_jobs_support.py
daal4py/sklearn/_utils.py
daal4py/sklearn/cluster/__init__.py
daal4py/sklearn/cluster/dbscan.py
daal4py/sklearn/cluster/k_means.py
daal4py/sklearn/cluster/tests/test_dbscan.py
daal4py/sklearn/decomposition/__init__.py
daal4py/sklearn/decomposition/_pca.py
daal4py/sklearn/ensemble/AdaBoostClassifier.py
daal4py/sklearn/ensemble/GBTDAAL.py
daal4py/sklearn/ensemble/__init__.py
daal4py/sklearn/ensemble/_forest.py
daal4py/sklearn/ensemble/tests/test_decision_forest.py
daal4py/sklearn/linear_model/__init__.py
daal4py/sklearn/linear_model/_coordinate_descent.py
daal4py/sklearn/linear_model/_linear.py
daal4py/sklearn/linear_model/_ridge.py
daal4py/sklearn/linear_model/coordinate_descent.py
daal4py/sklearn/linear_model/linear.py
daal4py/sklearn/linear_model/logistic_loss.py
daal4py/sklearn/linear_model/logistic_path.py
daal4py/sklearn/linear_model/ridge.py
daal4py/sklearn/linear_model/tests/test_enet.py
daal4py/sklearn/linear_model/tests/test_linear.py
daal4py/sklearn/linear_model/tests/test_ridge.py
daal4py/sklearn/manifold/__init__.py
daal4py/sklearn/manifold/_t_sne.py
daal4py/sklearn/metrics/__init__.py
daal4py/sklearn/metrics/_pairwise.py
daal4py/sklearn/metrics/_ranking.py
daal4py/sklearn/model_selection/__init__.py
daal4py/sklearn/model_selection/_split.py
daal4py/sklearn/model_selection/tests/test_split.py
daal4py/sklearn/monkeypatch/__init__.py
daal4py/sklearn/monkeypatch/dispatcher.py
daal4py/sklearn/monkeypatch/tests/_models_info.py
daal4py/sklearn/monkeypatch/tests/test_monkeypatch.py
daal4py/sklearn/monkeypatch/tests/test_patching.py
daal4py/sklearn/monkeypatch/tests/utils/_launch_algorithms.py
daal4py/sklearn/neighbors/__init__.py
scikit_learn_intelex-2025.10.1.dist-info/LICENSE.txt
scikit_learn_intelex-2025.10.1.dist-info/METADATA
scikit_learn_intelex-2025.10.1.dist-info/WHEEL
scikit_learn_intelex-2025.10.1.dist-info/top_level.txt
scikit_learn_intelex-2025.10.1.dist-info/RECORD
