Metadata-Version: 2.1
Name: scikit-learn-intelex
Version: 2025.10.1
Summary: Intel® Extension for Scikit-learn is a seamless way to speed up your Scikit-learn application.
Home-page: https://github.com/intel/scikit-learn-intelex
Author: Intel Corporation
Author-email: onedal.maintainers@intel.com
Maintainer-email: onedal.maintainers@intel.com
License: Apache v2.0
Project-URL: Bug Tracker, https://github.com/uxlfoundation/scikit-learn-intelex/issues
Project-URL: Documentation, https://uxlfoundation.github.io/scikit-learn-intelex/
Project-URL: Source Code, https://github.com/uxlfoundation/scikit-learn-intelex
Keywords: machine learning,scikit-learn,data science,data analytics
Platform: UNKNOWN
Classifier: Development Status :: 5 - Production/Stable
Classifier: Environment :: Console
Classifier: Intended Audience :: Developers
Classifier: Intended Audience :: Other Audience
Classifier: Intended Audience :: Science/Research
Classifier: Operating System :: Microsoft :: Windows
Classifier: Operating System :: POSIX :: Linux
Classifier: Programming Language :: Python :: 3.9
Classifier: Programming Language :: Python :: 3.10
Classifier: Programming Language :: Python :: 3.11
Classifier: Programming Language :: Python :: 3.12
Classifier: Programming Language :: Python :: 3.13
Classifier: Topic :: Scientific/Engineering
Classifier: Topic :: System
Classifier: Topic :: Software Development
Requires-Python: >=3.7
License-File: LICENSE.txt
Requires-Dist: daal (==2025.10.1)
Requires-Dist: numpy (>=1.19)
Requires-Dist: scikit-learn (>=0.22)
